servicenowpy/__init__.py
servicenowpy/exceptions.py
servicenowpy/servicenow.py
servicenowpy-0.1.0.dist-info/LICENSE
servicenowpy-0.1.0.dist-info/METADATA
servicenowpy-0.1.0.dist-info/WHEEL
servicenowpy-0.1.0.dist-info/top_level.txt
servicenowpy-0.1.0.dist-info/RECORD
