Metadata-Version: 2.1
Name: servicenowpy
Version: 0.1.0
Summary: ServiceNow Table API, easily
Home-page: UNKNOWN
Author: Henrique Santos
Author-email: henriquencmt@gmail.com
License: MIT
Project-URL: Bug Tracker, https://github.com/henriquencmt/servicenowpy/issues
Project-URL: Source Code, https://github.com/henriquencmt/servicenowpy
Project-URL: Documentation, https://servicenowpy.readthedocs.io
Keywords: servicenow
Platform: UNKNOWN
Classifier: Development Status :: 5 - Production/Stable
Classifier: Intended Audience :: Developers
Classifier: Operating System :: OS Independent
Classifier: License :: OSI Approved :: MIT License
Classifier: Programming Language :: Python :: 3
Requires-Python: >=3.8
License-File: LICENSE
Requires-Dist: requests (>=2.22.0)
